{
    "temp": [
        -63.71,
        -62.86,
        -62.01,
        -61.16,
        -60.31,
        -59.47,
        -58.62,
        -57.78,
        -56.98,
        -56.19,
        -55.39,
        -54.59,
        -54.06,
        -53.68,
        -53.3,
        -52.93,
        -52.74,
        -52.64,
        -52.55,
        -52.47,
        -52.48,
        -52.48,
        -52.46,
        -52.31,
        -52.16,
        -51.6,
        -50.57,
        -49.54,
        -48.07,
        -46.6,
        -44.89,
        -43.08,
        -41.09,
        -38.95,
        -36.76,
        -34.52,
        -32.32,
        -30.13,
        -28.05,
        -26.0,
        -24.03,
        -22.1,
        -20.23,
        -18.42,
        -16.65,
        -14.89,
        -13.29,
        -11.69,
        -10.07,
        -8.7,
        -7.39,
        -6.14,
        -4.97,
        -3.81,
        -2.57,
        -1.37,
        -0.24,
        0.42,
        0.71,
        0.89,
        1.41,
        1.65,
        1.15,
        0.37,
        -0.35,
        0.73,
        3.11
    ],
    "dew": [
        -88.54,
        -88.7,
        -88.86,
        -89.02,
        -89.18,
        -89.34,
        -89.5,
        -89.67,
        -89.89,
        -90.11,
        -90.34,
        -90.56,
        -89.79,
        -88.48,
        -87.16,
        -85.85,
        -83.89,
        -81.64,
        -79.38,
        -76.76,
        -72.96,
        -69.15,
        -65.66,
        -63.45,
        -61.25,
        -59.12,
        -57.09,
        -55.05,
        -53.06,
        -51.07,
        -49.01,
        -46.91,
        -44.72,
        -42.44,
        -40.1,
        -37.69,
        -35.3,
        -32.93,
        -30.69,
        -28.5,
        -26.43,
        -24.37,
        -22.31,
        -20.31,
        -18.37,
        -16.51,
        -14.68,
        -12.89,
        -11.17,
        -9.53,
        -8.01,
        -6.61,
        -5.32,
        -4.1,
        -2.83,
        -1.63,
        -0.48,
        0.16,
        0.4,
        0.6,
        0.97,
        0.97,
        0.31,
        -0.55,
        -1.09,
        -0.44,
        1.5
    ],
    "pres": [
        94.7,
        99.21,
        103.72,
        108.23,
        112.73,
        117.24,
        121.75,
        126.51,
        131.9,
        137.29,
        142.68,
        148.08,
        154.06,
        160.37,
        166.68,
        172.99,
        179.94,
        187.19,
        194.45,
        201.92,
        210.14,
        218.35,
        226.75,
        235.94,
        245.12,
        254.73,
        264.83,
        274.93,
        285.81,
        296.69,
        308.12,
        319.77,
        331.82,
        344.19,
        356.92,
        369.96,
        383.43,
        397.15,
        411.38,
        425.78,
        440.77,
        456.03,
        471.72,
        487.94,
        504.46,
        521.42,
        538.98,
        556.9,
        575.16,
        594.2,
        613.63,
        633.55,
        654.04,
        675.02,
        696.73,
        718.99,
        741.84,
        765.33,
        789.51,
        814.44,
        840.12,
        866.55,
        893.84,
        922.04,
        951.27,
        981.43,
        1011.91
    ],
    "uwnd": [
        29.06,
        28.44,
        27.81,
        27.18,
        26.55,
        25.92,
        25.29,
        25.54,
        28.05,
        30.55,
        33.06,
        35.56,
        38.09,
        40.62,
        43.15,
        45.68,
        46.45,
        46.39,
        46.34,
        46.14,
        45.43,
        44.73,
        44.15,
        44.09,
        44.03,
        43.23,
        41.58,
        39.93,
        38.35,
        36.76,
        34.88,
        32.87,
        30.54,
        27.96,
        25.68,
        23.66,
        22.25,
        21.24,
        20.66,
        20.2,
        20.02,
        19.89,
        19.85,
        19.45,
        18.88,
        18.09,
        16.81,
        15.37,
        13.9,
        12.68,
        11.47,
        10.5,
        9.85,
        9.24,
        8.83,
        8.24,
        7.57,
        6.94,
        6.36,
        5.53,
        3.16,
        0.96,
        0.72,
        -0.12,
        -2.01,
        -2.08,
        -1.27
    ],
    "vwnd": [
        7.08,
        7.1,
        7.12,
        7.13,
        7.15,
        7.17,
        7.18,
        6.54,
        4.19,
        1.84,
        -0.51,
        -2.86,
        -3.78,
        -3.9,
        -4.02,
        -4.14,
        -3.27,
        -1.94,
        -0.61,
        0.63,
        1.55,
        2.47,
        3.45,
        4.7,
        5.94,
        6.67,
        6.81,
        6.95,
        6.78,
        6.6,
        6.89,
        7.37,
        8.07,
        8.95,
        9.86,
        10.8,
        11.58,
        12.26,
        12.72,
        13.11,
        13.46,
        13.8,
        14.13,
        14.72,
        15.41,
        16.2,
        16.57,
        16.79,
        16.96,
        16.65,
        16.37,
        16.08,
        15.76,
        15.38,
        14.31,
        12.82,
        10.74,
        8.59,
        6.69,
        5.19,
        3.31,
        -0.99,
        -6.91,
        -10.22,
        -10.34,
        -8.82,
        -6.34
    ]
}