{
    "temp": [
        -57.29,
        -57.12,
        -56.94,
        -56.77,
        -56.59,
        -56.42,
        -56.24,
        -56.07,
        -55.89,
        -55.87,
        -55.86,
        -55.86,
        -55.85,
        -55.85,
        -55.89,
        -55.93,
        -55.98,
        -56.14,
        -56.51,
        -56.88,
        -57.25,
        -57.28,
        -57.31,
        -57.33,
        -56.94,
        -56.55,
        -55.82,
        -54.41,
        -53.01,
        -51.3,
        -49.57,
        -47.85,
        -46.15,
        -44.49,
        -42.88,
        -41.13,
        -39.26,
        -37.37,
        -35.47,
        -33.74,
        -32.07,
        -30.6,
        -29.17,
        -27.77,
        -26.4,
        -25.04,
        -23.72,
        -22.68,
        -21.75,
        -21.06,
        -20.64,
        -20.35,
        -20.82,
        -21.59,
        -22.12,
        -22.47,
        -21.97,
        -20.79,
        -19.12,
        -17.11,
        -14.93,
        -12.85,
        -10.58,
        -8.22,
        -5.76,
        -3.26,
        0.29
    ],
    "dew": [
        -89.75,
        -89.76,
        -89.78,
        -89.79,
        -89.81,
        -89.82,
        -89.83,
        -89.85,
        -89.86,
        -89.54,
        -89.18,
        -88.83,
        -88.47,
        -88.33,
        -88.71,
        -89.09,
        -89.47,
        -88.48,
        -85.14,
        -81.8,
        -78.46,
        -76.6,
        -74.76,
        -72.93,
        -72.71,
        -72.48,
        -72.23,
        -71.95,
        -71.67,
        -70.34,
        -68.91,
        -67.0,
        -64.82,
        -63.21,
        -62.09,
        -61.78,
        -62.14,
        -62.87,
        -63.79,
        -63.59,
        -62.97,
        -61.18,
        -59.26,
        -57.23,
        -55.59,
        -54.29,
        -53.26,
        -52.01,
        -50.84,
        -49.99,
        -49.48,
        -48.95,
        -44.25,
        -40.09,
        -33.65,
        -27.72,
        -24.9,
        -23.36,
        -21.35,
        -19.06,
        -16.79,
        -14.79,
        -13.22,
        -12.64,
        -12.62,
        -11.62,
        -7.47
    ],
    "pres": [
        89.38,
        93.79,
        98.2,
        102.61,
        107.02,
        111.43,
        115.84,
        120.25,
        124.66,
        129.98,
        135.38,
        140.77,
        146.16,
        151.84,
        158.21,
        164.59,
        170.96,
        177.7,
        185.09,
        192.48,
        199.87,
        208.26,
        216.67,
        225.08,
        234.46,
        243.83,
        253.52,
        263.79,
        274.06,
        285.04,
        296.08,
        307.62,
        319.42,
        331.63,
        344.19,
        357.16,
        370.47,
        384.25,
        398.28,
        412.91,
        427.74,
        443.17,
        459.02,
        475.22,
        492.12,
        509.41,
        527.11,
        545.5,
        564.43,
        583.89,
        603.95,
        624.65,
        646.17,
        668.5,
        691.62,
        715.57,
        740.35,
        765.89,
        792.15,
        819.13,
        846.75,
        875.05,
        904.14,
        933.9,
        964.34,
        995.3,
        1027.54
    ],
    "uwnd": [
        42.89,
        43.06,
        43.23,
        43.39,
        43.56,
        43.73,
        43.9,
        44.07,
        44.24,
        44.7,
        45.18,
        45.67,
        46.15,
        46.83,
        47.98,
        49.13,
        50.28,
        51.37,
        52.36,
        53.34,
        54.33,
        56.18,
        58.04,
        59.91,
        61.64,
        63.38,
        64.97,
        66.28,
        67.6,
        68.02,
        68.35,
        68.0,
        67.28,
        66.38,
        65.33,
        64.27,
        63.21,
        61.92,
        60.51,
        58.82,
        57.04,
        55.04,
        53.09,
        51.17,
        49.31,
        47.5,
        45.71,
        43.79,
        41.83,
        39.6,
        37.0,
        34.23,
        31.67,
        29.09,
        26.86,
        24.86,
        21.73,
        18.23,
        15.5,
        14.24,
        13.61,
        12.69,
        10.79,
        9.0,
        7.87,
        7.19,
        5.47
    ],
    "vwnd": [
        8.59,
        7.67,
        6.75,
        5.84,
        4.92,
        4.0,
        3.08,
        2.17,
        1.25,
        0.68,
        0.15,
        -0.39,
        -0.92,
        -1.27,
        -1.14,
        -1.02,
        -0.89,
        -1.14,
        -2.02,
        -2.91,
        -3.8,
        -5.2,
        -6.6,
        -8.01,
        -9.58,
        -11.15,
        -12.64,
        -13.97,
        -15.3,
        -16.05,
        -16.74,
        -16.43,
        -15.55,
        -14.31,
        -12.75,
        -11.51,
        -10.55,
        -10.11,
        -9.94,
        -10.06,
        -10.25,
        -10.59,
        -11.15,
        -11.87,
        -12.6,
        -13.3,
        -13.9,
        -14.02,
        -14.07,
        -13.88,
        -13.42,
        -12.89,
        -11.7,
        -10.37,
        -8.87,
        -7.26,
        -4.91,
        -2.33,
        -0.18,
        1.01,
        1.5,
        1.44,
        0.79,
        0.18,
        -0.02,
        0.11,
        0.18
    ]
}