{
    "temp": [
        -59.69,
        -59.56,
        -59.43,
        -59.3,
        -59.16,
        -59.03,
        -58.9,
        -58.77,
        -60.19,
        -61.62,
        -63.06,
        -64.49,
        -65.06,
        -64.71,
        -64.35,
        -63.99,
        -63.11,
        -62.04,
        -60.97,
        -59.64,
        -57.99,
        -56.33,
        -54.55,
        -52.63,
        -50.71,
        -48.72,
        -46.71,
        -44.66,
        -42.49,
        -40.32,
        -38.24,
        -36.17,
        -34.32,
        -32.57,
        -30.83,
        -29.09,
        -27.4,
        -25.73,
        -24.06,
        -22.39,
        -20.8,
        -19.26,
        -17.83,
        -16.4,
        -14.97,
        -13.53,
        -12.14,
        -10.74,
        -9.31,
        -7.87,
        -6.3,
        -4.57,
        -2.63,
        -0.68,
        1.28,
        3.13,
        4.88,
        6.54,
        8.28,
        10.34,
        12.6,
        14.94,
        17.12,
        18.46,
        18.39,
        18.36,
        18.92
    ],
    "dew": [
        -87.33,
        -86.53,
        -85.73,
        -84.94,
        -84.14,
        -83.34,
        -82.54,
        -81.75,
        -80.44,
        -79.12,
        -77.81,
        -76.5,
        -75.26,
        -74.11,
        -72.95,
        -71.8,
        -70.37,
        -68.84,
        -67.31,
        -65.49,
        -63.28,
        -61.08,
        -58.95,
        -56.91,
        -54.87,
        -52.73,
        -50.57,
        -48.38,
        -46.11,
        -43.83,
        -41.73,
        -39.64,
        -37.82,
        -36.11,
        -34.26,
        -32.33,
        -30.79,
        -29.46,
        -28.1,
        -26.74,
        -25.35,
        -23.92,
        -22.42,
        -21.02,
        -19.68,
        -18.42,
        -17.24,
        -16.02,
        -14.62,
        -12.82,
        -11.35,
        -10.46,
        -10.23,
        -9.26,
        -7.76,
        -5.02,
        -1.93,
        0.89,
        3.39,
        5.52,
        7.07,
        7.91,
        8.1,
        8.87,
        11.98,
        14.98,
        16.8
    ],
    "pres": [
        93.73,
        98.19,
        102.66,
        107.12,
        111.59,
        116.05,
        120.51,
        124.98,
        130.51,
        136.05,
        141.58,
        147.12,
        153.2,
        159.87,
        166.54,
        173.21,
        180.55,
        188.13,
        195.72,
        203.67,
        212.1,
        220.54,
        229.33,
        238.53,
        247.73,
        257.5,
        267.45,
        277.57,
        288.22,
        298.86,
        310.12,
        321.46,
        333.28,
        345.32,
        357.79,
        370.53,
        383.74,
        397.18,
        411.19,
        425.35,
        440.14,
        455.16,
        470.67,
        486.71,
        503.06,
        519.89,
        537.26,
        555.03,
        573.24,
        592.11,
        611.4,
        631.15,
        651.4,
        672.22,
        693.53,
        715.38,
        737.72,
        760.57,
        784.01,
        808.0,
        832.5,
        857.53,
        883.13,
        909.32,
        936.22,
        963.9,
        992.54
    ],
    "uwnd": [
        18.47,
        18.94,
        19.41,
        19.88,
        20.35,
        20.82,
        21.28,
        21.75,
        23.33,
        24.92,
        26.5,
        28.09,
        30.07,
        32.48,
        34.9,
        37.31,
        40.46,
        43.89,
        47.32,
        48.89,
        48.03,
        47.17,
        45.93,
        44.26,
        42.59,
        39.13,
        35.07,
        31.46,
        29.23,
        27.0,
        27.84,
        29.05,
        29.66,
        30.0,
        28.69,
        26.32,
        24.26,
        22.35,
        21.05,
        19.9,
        19.07,
        18.14,
        16.98,
        16.16,
        15.51,
        14.95,
        14.44,
        13.92,
        13.31,
        12.34,
        11.41,
        10.56,
        9.82,
        9.48,
        9.46,
        9.42,
        9.27,
        8.9,
        8.44,
        8.41,
        8.85,
        9.61,
        10.51,
        11.63,
        11.38,
        7.91,
        1.58
    ],
    "vwnd": [
        5.25,
        5.3,
        5.35,
        5.4,
        5.45,
        5.5,
        5.55,
        5.6,
        6.03,
        6.47,
        6.9,
        7.33,
        7.5,
        7.39,
        7.27,
        7.16,
        12.15,
        19.01,
        25.86,
        28.26,
        24.85,
        21.45,
        18.42,
        15.82,
        13.21,
        14.58,
        17.26,
        19.63,
        21.02,
        22.41,
        20.53,
        18.25,
        15.45,
        12.42,
        10.9,
        10.34,
        10.68,
        11.5,
        11.79,
        11.92,
        11.34,
        10.52,
        9.23,
        8.21,
        7.32,
        6.55,
        5.92,
        5.36,
        4.82,
        4.32,
        3.65,
        2.72,
        1.49,
        0.35,
        -0.83,
        -1.01,
        -0.51,
        0.3,
        1.07,
        1.6,
        2.36,
        3.78,
        6.05,
        8.98,
        12.09,
        12.3,
        4.47
    ]
}