{
    "temp": [
        -67.3,
        -66.35,
        -65.4,
        -64.44,
        -63.49,
        -62.54,
        -61.59,
        -60.38,
        -58.77,
        -57.16,
        -55.55,
        -53.94,
        -54.54,
        -55.78,
        -57.02,
        -58.26,
        -58.62,
        -58.79,
        -58.97,
        -58.0,
        -55.9,
        -53.8,
        -51.66,
        -49.49,
        -47.31,
        -45.09,
        -42.86,
        -40.66,
        -38.58,
        -36.51,
        -34.57,
        -32.67,
        -30.8,
        -28.95,
        -27.1,
        -25.23,
        -23.37,
        -21.53,
        -19.78,
        -18.11,
        -16.59,
        -15.12,
        -13.8,
        -12.52,
        -11.29,
        -10.09,
        -8.9,
        -7.72,
        -6.48,
        -5.2,
        -3.86,
        -2.43,
        -0.92,
        1.02,
        3.21,
        5.32,
        7.08,
        8.56,
        9.68,
        10.38,
        11.19,
        12.35,
        14.07,
        16.25,
        18.48,
        20.77,
        21.55
    ],
    "dew": [
        -81.23,
        -81.78,
        -82.32,
        -82.86,
        -83.41,
        -83.95,
        -84.49,
        -83.6,
        -80.52,
        -77.44,
        -74.36,
        -71.28,
        -71.02,
        -71.61,
        -72.19,
        -72.77,
        -70.99,
        -68.73,
        -66.47,
        -64.02,
        -61.37,
        -58.72,
        -56.23,
        -53.91,
        -51.59,
        -49.22,
        -46.85,
        -44.52,
        -42.37,
        -40.22,
        -38.29,
        -36.4,
        -34.47,
        -32.51,
        -30.53,
        -28.53,
        -26.51,
        -24.47,
        -22.54,
        -20.67,
        -19.02,
        -17.44,
        -16.09,
        -14.8,
        -13.63,
        -12.62,
        -11.74,
        -11.05,
        -10.47,
        -9.96,
        -9.31,
        -7.68,
        -5.56,
        -3.01,
        -0.47,
        1.44,
        2.35,
        2.78,
        2.86,
        3.14,
        4.41,
        6.35,
        8.31,
        9.79,
        10.96,
        12.36,
        15.27
    ],
    "pres": [
        94.67,
        99.26,
        103.85,
        108.45,
        113.04,
        117.63,
        122.23,
        127.14,
        132.55,
        137.95,
        143.36,
        148.77,
        154.9,
        161.24,
        167.59,
        173.94,
        181.26,
        188.78,
        196.29,
        204.23,
        212.58,
        220.93,
        229.65,
        238.73,
        247.8,
        257.41,
        267.2,
        277.13,
        287.58,
        298.03,
        309.05,
        320.21,
        331.75,
        343.6,
        355.76,
        368.29,
        381.13,
        394.33,
        407.92,
        421.8,
        436.17,
        450.72,
        465.95,
        481.47,
        497.42,
        513.92,
        530.77,
        548.1,
        566.03,
        584.37,
        603.16,
        622.51,
        642.39,
        662.76,
        683.59,
        704.84,
        726.63,
        748.99,
        771.94,
        795.52,
        819.75,
        844.62,
        870.08,
        896.11,
        922.7,
        949.84,
        977.56
    ],
    "uwnd": [
        20.45,
        20.2,
        19.95,
        19.7,
        19.45,
        19.2,
        18.95,
        19.15,
        20.02,
        20.9,
        21.77,
        22.64,
        24.41,
        26.44,
        28.47,
        30.5,
        31.58,
        32.46,
        33.35,
        33.56,
        33.12,
        32.68,
        31.39,
        29.3,
        27.21,
        25.47,
        23.86,
        22.46,
        21.9,
        21.34,
        21.4,
        21.59,
        21.82,
        22.07,
        22.17,
        22.11,
        21.73,
        20.99,
        20.01,
        18.86,
        17.47,
        16.01,
        14.4,
        13.03,
        12.02,
        11.12,
        10.42,
        10.06,
        10.08,
        10.42,
        11.11,
        12.16,
        13.39,
        13.85,
        13.62,
        12.85,
        11.2,
        8.6,
        5.14,
        0.75,
        -3.15,
        -5.51,
        -6.3,
        -6.02,
        -5.34,
        -4.13,
        -2.97
    ],
    "vwnd": [
        16.71,
        16.89,
        17.07,
        17.25,
        17.43,
        17.61,
        17.79,
        17.25,
        15.61,
        13.98,
        12.34,
        10.71,
        13.57,
        17.75,
        21.94,
        26.13,
        27.96,
        29.32,
        30.67,
        31.06,
        30.51,
        29.95,
        29.64,
        29.56,
        29.47,
        29.55,
        29.68,
        29.81,
        29.95,
        30.09,
        30.16,
        30.22,
        30.29,
        30.36,
        30.48,
        30.65,
        30.92,
        31.29,
        31.86,
        32.59,
        33.48,
        34.44,
        35.45,
        36.16,
        36.42,
        36.38,
        36.02,
        35.16,
        34.08,
        32.8,
        31.31,
        29.56,
        27.68,
        26.03,
        24.78,
        24.18,
        24.54,
        24.39,
        23.37,
        21.78,
        20.87,
        20.36,
        19.16,
        17.19,
        14.98,
        11.47,
        3.68
    ]
}