{
    "temp": [
        -61.58,
        -62.41,
        -63.24,
        -64.07,
        -64.9,
        -65.73,
        -66.56,
        -67.28,
        -67.66,
        -68.04,
        -68.42,
        -68.79,
        -67.42,
        -65.87,
        -64.31,
        -62.77,
        -61.28,
        -59.8,
        -58.32,
        -56.47,
        -54.55,
        -52.63,
        -50.65,
        -48.64,
        -46.63,
        -44.54,
        -42.45,
        -40.27,
        -38.02,
        -35.79,
        -33.67,
        -31.56,
        -29.62,
        -27.7,
        -25.84,
        -24.0,
        -22.2,
        -20.41,
        -18.54,
        -16.68,
        -14.93,
        -13.27,
        -11.77,
        -10.24,
        -8.71,
        -7.21,
        -5.72,
        -4.26,
        -2.99,
        -2.04,
        -1.15,
        -0.16,
        1.0,
        2.51,
        4.17,
        5.69,
        6.94,
        8.17,
        9.27,
        10.29,
        11.3,
        12.22,
        13.46,
        14.73,
        14.91,
        14.65,
        14.5
    ],
    "dew": [
        -90.69,
        -88.41,
        -86.14,
        -83.87,
        -81.59,
        -79.32,
        -77.05,
        -75.27,
        -74.95,
        -74.62,
        -74.3,
        -73.97,
        -72.55,
        -71.0,
        -69.46,
        -67.9,
        -66.28,
        -64.66,
        -63.05,
        -61.13,
        -59.15,
        -57.17,
        -55.32,
        -53.49,
        -51.72,
        -50.58,
        -49.45,
        -48.65,
        -48.14,
        -47.62,
        -47.08,
        -46.53,
        -45.54,
        -44.51,
        -43.1,
        -41.59,
        -38.97,
        -36.05,
        -31.83,
        -27.48,
        -23.59,
        -19.87,
        -16.43,
        -13.18,
        -10.1,
        -7.69,
        -5.81,
        -4.33,
        -3.05,
        -2.1,
        -1.21,
        -0.23,
        0.87,
        2.3,
        3.84,
        5.24,
        6.41,
        7.6,
        8.74,
        9.61,
        10.14,
        10.71,
        11.98,
        13.14,
        12.87,
        12.98,
        14.14
    ],
    "pres": [
        94.24,
        98.8,
        103.36,
        107.92,
        112.48,
        117.04,
        121.6,
        126.46,
        132.21,
        137.95,
        143.7,
        149.45,
        156.04,
        162.73,
        169.41,
        176.23,
        183.76,
        191.29,
        198.83,
        207.03,
        215.35,
        223.68,
        232.63,
        241.69,
        250.82,
        260.62,
        270.43,
        280.58,
        291.05,
        301.61,
        312.76,
        323.91,
        335.67,
        347.49,
        359.85,
        372.36,
        385.4,
        398.59,
        412.38,
        426.3,
        440.75,
        455.45,
        470.59,
        486.23,
        502.16,
        518.57,
        535.42,
        552.64,
        570.38,
        588.65,
        607.37,
        626.57,
        646.38,
        666.77,
        687.6,
        708.93,
        730.81,
        753.25,
        776.27,
        799.92,
        824.22,
        849.15,
        874.74,
        900.98,
        927.93,
        955.74,
        984.56
    ],
    "uwnd": [
        6.99,
        9.8,
        12.62,
        15.44,
        18.25,
        21.07,
        23.88,
        25.66,
        24.39,
        23.13,
        21.86,
        20.59,
        21.9,
        23.48,
        25.05,
        26.44,
        26.86,
        27.28,
        27.7,
        27.04,
        26.19,
        25.34,
        25.0,
        24.75,
        24.58,
        25.19,
        25.8,
        26.79,
        28.11,
        29.43,
        30.75,
        32.06,
        33.06,
        34.02,
        33.69,
        33.03,
        32.52,
        32.06,
        31.74,
        31.41,
        30.74,
        29.77,
        28.27,
        26.62,
        24.93,
        23.3,
        21.85,
        20.51,
        19.08,
        17.53,
        15.93,
        14.3,
        12.62,
        11.15,
        9.82,
        8.43,
        7.15,
        6.78,
        7.62,
        9.84,
        11.28,
        11.11,
        9.56,
        7.32,
        3.24,
        0.1,
        -1.09
    ],
    "vwnd": [
        6.32,
        8.42,
        10.52,
        12.63,
        14.73,
        16.83,
        18.94,
        20.72,
        21.59,
        22.45,
        23.31,
        24.17,
        24.04,
        23.8,
        23.57,
        23.52,
        24.46,
        25.41,
        26.35,
        26.86,
        27.3,
        27.74,
        27.03,
        26.11,
        25.11,
        23.2,
        21.28,
        19.92,
        19.03,
        18.3,
        18.49,
        18.68,
        18.72,
        18.74,
        18.19,
        17.48,
        16.4,
        15.23,
        14.74,
        14.38,
        14.56,
        14.94,
        15.66,
        16.38,
        17.12,
        18.01,
        19.42,
        21.14,
        22.65,
        23.79,
        24.58,
        24.94,
        24.62,
        23.8,
        22.68,
        21.32,
        19.78,
        18.16,
        16.51,
        14.37,
        11.78,
        8.66,
        6.15,
        6.42,
        6.75,
        3.73,
        0.8
    ]
}