{
    "temp": [
        -60.36,
        -60.38,
        -60.4,
        -60.42,
        -60.44,
        -60.46,
        -60.52,
        -60.73,
        -60.95,
        -61.16,
        -61.37,
        -61.72,
        -62.14,
        -62.56,
        -62.98,
        -61.79,
        -60.35,
        -58.92,
        -57.18,
        -55.2,
        -53.22,
        -51.32,
        -49.47,
        -47.62,
        -45.57,
        -43.46,
        -41.35,
        -39.24,
        -37.12,
        -35.08,
        -33.05,
        -31.06,
        -29.09,
        -27.22,
        -25.44,
        -23.8,
        -22.27,
        -20.75,
        -19.22,
        -17.71,
        -16.2,
        -14.71,
        -13.28,
        -11.9,
        -10.52,
        -9.12,
        -7.69,
        -6.2,
        -4.54,
        -2.79,
        -1.09,
        0.39,
        1.86,
        3.32,
        4.79,
        6.27,
        7.77,
        9.86,
        11.98,
        13.8,
        15.09,
        16.08,
        17.13,
        18.3,
        19.11,
        18.44,
        18.14
    ],
    "dew": [
        -87.75,
        -87.43,
        -87.11,
        -86.79,
        -86.47,
        -86.15,
        -85.51,
        -83.55,
        -81.59,
        -79.63,
        -77.67,
        -75.51,
        -73.26,
        -71.0,
        -68.74,
        -66.89,
        -65.09,
        -63.29,
        -61.45,
        -59.56,
        -57.68,
        -55.76,
        -53.81,
        -51.86,
        -49.68,
        -47.42,
        -45.38,
        -43.94,
        -42.5,
        -41.05,
        -39.59,
        -37.41,
        -34.82,
        -32.12,
        -29.33,
        -26.94,
        -24.89,
        -23.0,
        -21.21,
        -19.56,
        -17.94,
        -16.33,
        -15.5,
        -15.45,
        -16.08,
        -16.35,
        -16.11,
        -15.5,
        -13.28,
        -10.14,
        -7.35,
        -4.25,
        -1.59,
        0.6,
        2.27,
        3.36,
        3.9,
        3.41,
        3.29,
        4.05,
        6.37,
        10.69,
        15.06,
        17.93,
        18.92,
        18.01,
        16.39
    ],
    "pres": [
        98.87,
        103.37,
        107.87,
        112.37,
        116.87,
        121.38,
        126.08,
        131.6,
        137.11,
        142.63,
        148.15,
        154.38,
        160.95,
        167.53,
        174.11,
        181.54,
        189.09,
        196.65,
        204.63,
        212.95,
        221.27,
        230.01,
        239.08,
        248.16,
        257.82,
        267.64,
        277.63,
        288.12,
        298.61,
        309.7,
        320.88,
        332.49,
        344.35,
        356.57,
        369.12,
        382.03,
        395.27,
        408.96,
        422.9,
        437.39,
        452.08,
        467.38,
        483.03,
        499.03,
        515.62,
        532.59,
        549.98,
        567.94,
        586.36,
        605.2,
        624.42,
        644.34,
        664.68,
        685.51,
        706.88,
        728.77,
        751.2,
        774.25,
        797.8,
        821.9,
        846.58,
        871.88,
        897.79,
        924.32,
        951.53,
        979.55,
        1008.5
    ],
    "uwnd": [
        10.65,
        12.13,
        13.6,
        15.08,
        16.55,
        18.03,
        19.58,
        21.46,
        23.33,
        25.2,
        27.07,
        28.43,
        29.53,
        30.63,
        31.73,
        31.85,
        31.83,
        31.8,
        32.34,
        33.34,
        34.34,
        34.41,
        33.72,
        33.04,
        31.69,
        30.18,
        28.69,
        27.28,
        25.86,
        24.24,
        22.58,
        21.5,
        20.75,
        20.16,
        19.72,
        19.25,
        18.75,
        18.45,
        18.26,
        18.15,
        18.01,
        17.65,
        17.22,
        16.7,
        16.14,
        15.64,
        15.21,
        14.76,
        14.17,
        13.5,
        12.8,
        11.95,
        11.2,
        10.76,
        10.62,
        10.54,
        10.52,
        10.49,
        10.34,
        10.23,
        10.06,
        9.99,
        10.91,
        13.09,
        13.45,
        8.28,
        1.54
    ],
    "vwnd": [
        -4.22,
        -4.61,
        -4.99,
        -5.37,
        -5.75,
        -6.14,
        -6.45,
        -6.5,
        -6.54,
        -6.58,
        -6.63,
        -4.98,
        -2.49,
        0.01,
        2.51,
        3.9,
        5.11,
        6.32,
        6.62,
        6.17,
        5.73,
        5.8,
        6.29,
        6.78,
        7.26,
        7.72,
        8.01,
        7.74,
        7.48,
        6.97,
        6.43,
        6.18,
        6.12,
        6.15,
        6.28,
        6.49,
        6.75,
        7.17,
        7.67,
        8.34,
        9.06,
        9.91,
        10.49,
        10.82,
        10.93,
        10.83,
        10.51,
        10.22,
        10.18,
        10.27,
        10.3,
        10.36,
        10.34,
        10.2,
        10.15,
        10.49,
        11.15,
        12.44,
        13.24,
        13.18,
        12.68,
        12.62,
        13.34,
        14.7,
        14.87,
        11.62,
        4.7
    ]
}