{
    "temp": [
        -66.25,
        -66.95,
        -67.66,
        -68.36,
        -69.06,
        -69.77,
        -70.47,
        -69.69,
        -68.84,
        -67.99,
        -67.14,
        -65.86,
        -64.28,
        -62.71,
        -61.13,
        -59.18,
        -57.16,
        -55.13,
        -53.26,
        -51.57,
        -49.88,
        -48.07,
        -46.09,
        -44.11,
        -42.21,
        -40.36,
        -38.5,
        -36.63,
        -34.75,
        -32.81,
        -30.84,
        -28.86,
        -26.86,
        -24.85,
        -22.83,
        -20.86,
        -19.12,
        -17.48,
        -16.11,
        -14.8,
        -13.59,
        -12.44,
        -11.3,
        -9.93,
        -8.55,
        -7.14,
        -5.61,
        -4.14,
        -2.74,
        -1.47,
        -0.19,
        1.13,
        2.58,
        4.46,
        6.54,
        8.23,
        9.72,
        11.12,
        12.62,
        14.42,
        16.28,
        17.93,
        19.51,
        21.61,
        24.01,
        26.04,
        28.11
    ],
    "dew": [
        -84.83,
        -83.77,
        -82.72,
        -81.67,
        -80.61,
        -79.56,
        -78.5,
        -77.79,
        -77.1,
        -76.4,
        -75.71,
        -74.55,
        -73.08,
        -71.61,
        -70.14,
        -68.25,
        -66.27,
        -64.29,
        -62.2,
        -59.98,
        -57.75,
        -55.61,
        -53.61,
        -51.61,
        -49.05,
        -46.11,
        -43.17,
        -40.9,
        -38.63,
        -36.57,
        -34.64,
        -32.95,
        -31.72,
        -30.52,
        -29.4,
        -28.11,
        -26.03,
        -23.83,
        -21.3,
        -18.88,
        -16.62,
        -14.65,
        -12.82,
        -11.27,
        -9.78,
        -8.34,
        -6.81,
        -5.32,
        -3.86,
        -2.42,
        -1.26,
        -0.34,
        0.33,
        0.67,
        0.78,
        2.49,
        4.71,
        6.89,
        8.37,
        8.69,
        9.29,
        11.12,
        13.67,
        15.03,
        15.69,
        16.56,
        19.85
    ],
    "pres": [
        96.61,
        101.31,
        106.01,
        110.71,
        115.41,
        120.11,
        124.81,
        130.49,
        136.22,
        141.95,
        147.68,
        153.95,
        160.57,
        167.2,
        173.83,
        181.11,
        188.53,
        195.95,
        203.72,
        211.9,
        220.08,
        228.56,
        237.48,
        246.41,
        255.78,
        265.45,
        275.12,
        285.47,
        295.82,
        306.59,
        317.64,
        328.91,
        340.63,
        352.49,
        364.87,
        377.37,
        390.42,
        403.65,
        417.38,
        431.41,
        445.81,
        460.72,
        475.88,
        491.73,
        507.87,
        524.31,
        541.46,
        558.94,
        576.78,
        595.25,
        614.19,
        633.59,
        653.46,
        673.89,
        694.8,
        716.23,
        738.17,
        760.62,
        783.63,
        807.21,
        831.35,
        856.03,
        881.29,
        907.13,
        933.51,
        960.44,
        987.5
    ],
    "uwnd": [
        9.77,
        11.2,
        12.63,
        14.06,
        15.5,
        16.93,
        18.36,
        16.87,
        15.25,
        13.63,
        12.01,
        10.92,
        10.2,
        9.47,
        8.74,
        8.7,
        8.81,
        8.92,
        8.92,
        8.78,
        8.64,
        8.23,
        7.4,
        6.58,
        6.4,
        6.67,
        6.93,
        7.16,
        7.38,
        7.51,
        7.59,
        7.63,
        7.59,
        7.6,
        7.79,
        8.03,
        8.54,
        9.18,
        10.19,
        11.26,
        12.39,
        13.32,
        14.09,
        13.64,
        13.18,
        12.71,
        13.03,
        13.55,
        14.28,
        15.59,
        16.61,
        17.33,
        17.71,
        17.65,
        17.25,
        16.61,
        15.68,
        14.41,
        12.7,
        10.53,
        8.09,
        5.51,
        3.21,
        2.06,
        2.31,
        2.39,
        1.13
    ],
    "vwnd": [
        -7.75,
        -7.1,
        -6.45,
        -5.81,
        -5.16,
        -4.52,
        -3.87,
        -3.22,
        -2.57,
        -1.93,
        -1.28,
        -1.94,
        -3.48,
        -5.03,
        -6.57,
        -6.87,
        -6.9,
        -6.93,
        -7.37,
        -8.3,
        -9.24,
        -9.64,
        -9.23,
        -8.83,
        -8.19,
        -7.39,
        -6.61,
        -7.18,
        -7.74,
        -8.46,
        -9.3,
        -9.96,
        -10.29,
        -10.59,
        -10.75,
        -10.88,
        -10.87,
        -10.77,
        -10.38,
        -9.78,
        -8.91,
        -7.57,
        -6.03,
        -4.56,
        -3.17,
        -1.88,
        -1.48,
        -1.21,
        -1.03,
        -0.93,
        -0.76,
        -0.45,
        -0.01,
        0.39,
        0.69,
        0.04,
        -1.12,
        -2.53,
        -3.69,
        -3.9,
        -3.25,
        -1.95,
        -0.56,
        0.08,
        0.07,
        0.05,
        1.69
    ]
}