{
    "temp": [
        -67.53,
        -66.78,
        -66.03,
        -65.29,
        -64.54,
        -63.79,
        -63.05,
        -62.5,
        -62.17,
        -61.84,
        -61.51,
        -61.18,
        -60.98,
        -60.78,
        -60.58,
        -60.26,
        -59.23,
        -58.19,
        -57.16,
        -55.31,
        -53.27,
        -51.22,
        -49.22,
        -47.22,
        -45.23,
        -43.15,
        -41.07,
        -39.02,
        -37.03,
        -35.04,
        -33.26,
        -31.49,
        -29.63,
        -27.76,
        -25.96,
        -24.21,
        -22.45,
        -20.68,
        -18.9,
        -17.12,
        -15.49,
        -13.91,
        -12.47,
        -11.04,
        -9.63,
        -8.17,
        -6.63,
        -5.01,
        -3.26,
        -1.46,
        0.4,
        2.34,
        4.29,
        5.89,
        7.28,
        8.58,
        9.9,
        11.4,
        13.01,
        14.46,
        15.91,
        17.25,
        18.38,
        19.15,
        19.68,
        19.61,
        19.48
    ],
    "dew": [
        -84.81,
        -83.45,
        -82.1,
        -80.75,
        -79.4,
        -78.05,
        -76.69,
        -76.05,
        -76.16,
        -76.27,
        -76.38,
        -76.49,
        -74.86,
        -73.18,
        -71.51,
        -69.69,
        -67.05,
        -64.41,
        -61.77,
        -59.74,
        -57.86,
        -55.97,
        -54.49,
        -53.13,
        -51.77,
        -50.64,
        -49.51,
        -47.96,
        -45.86,
        -43.76,
        -41.37,
        -38.99,
        -37.46,
        -36.18,
        -34.88,
        -33.56,
        -31.57,
        -29.23,
        -27.07,
        -24.97,
        -22.68,
        -20.36,
        -17.92,
        -16.14,
        -14.81,
        -13.67,
        -12.58,
        -11.51,
        -9.75,
        -7.76,
        -5.82,
        -4.37,
        -3.25,
        -0.49,
        2.89,
        6.19,
        9.39,
        10.88,
        12.1,
        13.48,
        15.2,
        16.68,
        18.02,
        18.82,
        18.36,
        18.26,
        17.71
    ],
    "pres": [
        95.09,
        99.68,
        104.27,
        108.86,
        113.45,
        118.04,
        122.63,
        127.69,
        133.23,
        138.78,
        144.32,
        149.87,
        156.38,
        162.91,
        169.44,
        176.12,
        183.59,
        191.07,
        198.54,
        206.66,
        214.93,
        223.2,
        232.04,
        241.04,
        250.04,
        259.77,
        269.5,
        279.52,
        289.93,
        300.35,
        311.46,
        322.57,
        334.23,
        346.04,
        358.3,
        370.8,
        383.74,
        396.92,
        410.62,
        424.48,
        438.94,
        453.59,
        468.75,
        484.33,
        500.21,
        516.72,
        533.56,
        550.77,
        568.59,
        586.79,
        605.39,
        624.46,
        644.02,
        664.07,
        684.58,
        705.56,
        727.07,
        749.15,
        771.77,
        794.93,
        818.65,
        842.94,
        867.83,
        893.36,
        919.56,
        946.52,
        974.5
    ],
    "uwnd": [
        5.62,
        6.96,
        8.3,
        9.64,
        10.98,
        12.32,
        13.66,
        15.07,
        16.55,
        18.03,
        19.51,
        20.99,
        19.75,
        18.45,
        17.14,
        15.62,
        12.89,
        10.15,
        7.41,
        8.11,
        9.63,
        11.15,
        12.39,
        13.54,
        14.69,
        15.43,
        16.17,
        16.61,
        16.68,
        16.72,
        16.14,
        15.55,
        15.13,
        14.75,
        14.5,
        14.3,
        14.04,
        13.75,
        13.37,
        12.97,
        12.59,
        12.2,
        11.8,
        11.82,
        12.14,
        12.41,
        12.6,
        12.69,
        12.46,
        12.04,
        11.52,
        11.05,
        10.56,
        9.59,
        8.65,
        8.32,
        8.93,
        10.19,
        11.08,
        11.14,
        10.17,
        8.8,
        7.01,
        4.31,
        -0.37,
        -5.6,
        -3.53
    ],
    "vwnd": [
        0.53,
        0.55,
        0.56,
        0.58,
        0.6,
        0.61,
        0.63,
        1.12,
        2.12,
        3.12,
        4.12,
        5.12,
        6.54,
        7.96,
        9.39,
        10.29,
        8.22,
        6.15,
        4.07,
        3.24,
        2.7,
        2.17,
        2.71,
        3.55,
        4.4,
        4.83,
        5.27,
        5.58,
        5.72,
        5.87,
        6.0,
        6.13,
        6.21,
        6.28,
        6.35,
        6.43,
        6.41,
        6.34,
        6.13,
        5.89,
        5.67,
        5.45,
        5.24,
        5.16,
        5.17,
        5.49,
        6.01,
        6.74,
        7.63,
        8.6,
        9.23,
        8.89,
        8.07,
        7.3,
        6.88,
        7.19,
        8.4,
        8.5,
        7.91,
        6.73,
        5.93,
        5.15,
        3.47,
        0.38,
        -3.58,
        -6.23,
        -3.48
    ]
}