{
    "temp": [
        -71.78,
        -71.61,
        -71.44,
        -71.27,
        -71.1,
        -70.93,
        -70.65,
        -69.86,
        -69.08,
        -68.3,
        -67.52,
        -66.65,
        -65.78,
        -64.9,
        -63.91,
        -61.94,
        -59.97,
        -58.0,
        -55.92,
        -53.82,
        -51.71,
        -49.48,
        -47.21,
        -44.95,
        -42.92,
        -40.9,
        -38.91,
        -36.97,
        -35.03,
        -33.26,
        -31.5,
        -29.74,
        -27.97,
        -26.21,
        -24.44,
        -22.72,
        -21.02,
        -19.4,
        -17.8,
        -16.27,
        -14.78,
        -13.38,
        -11.93,
        -10.46,
        -8.92,
        -7.46,
        -6.06,
        -4.66,
        -3.52,
        -2.51,
        -1.5,
        -0.57,
        0.37,
        1.53,
        2.82,
        4.01,
        5.11,
        6.34,
        7.74,
        9.44,
        11.17,
        12.65,
        13.72,
        13.91,
        13.86,
        14.42,
        16.0
    ],
    "dew": [
        -83.1,
        -82.39,
        -81.68,
        -80.97,
        -80.27,
        -79.56,
        -78.78,
        -77.67,
        -76.56,
        -75.46,
        -74.35,
        -72.93,
        -71.45,
        -69.97,
        -68.43,
        -66.32,
        -64.22,
        -62.11,
        -59.96,
        -57.8,
        -55.63,
        -53.36,
        -51.05,
        -48.75,
        -46.59,
        -44.43,
        -42.33,
        -40.29,
        -38.26,
        -36.39,
        -34.53,
        -32.64,
        -30.74,
        -28.82,
        -26.9,
        -25.01,
        -23.15,
        -21.39,
        -19.66,
        -18.02,
        -16.39,
        -14.81,
        -13.16,
        -11.45,
        -9.73,
        -8.05,
        -6.42,
        -4.92,
        -3.69,
        -2.62,
        -1.57,
        -0.63,
        0.32,
        1.48,
        2.76,
        3.94,
        5.03,
        6.23,
        7.58,
        9.31,
        11.06,
        12.56,
        13.6,
        13.79,
        13.76,
        14.28,
        15.3
    ],
    "pres": [
        97.44,
        102.18,
        106.93,
        111.67,
        116.41,
        121.16,
        126.09,
        131.84,
        137.58,
        143.33,
        149.07,
        155.61,
        162.3,
        168.99,
        175.77,
        183.32,
        190.86,
        198.41,
        206.54,
        214.83,
        223.12,
        231.97,
        240.97,
        249.97,
        259.69,
        269.42,
        279.43,
        289.83,
        300.25,
        311.36,
        322.47,
        334.12,
        345.94,
        358.2,
        370.71,
        383.67,
        396.86,
        410.56,
        424.42,
        438.91,
        453.6,
        468.83,
        484.47,
        500.4,
        516.94,
        533.85,
        551.16,
        568.99,
        587.33,
        606.12,
        625.34,
        645.31,
        665.76,
        686.76,
        708.31,
        730.4,
        753.1,
        776.42,
        800.3,
        824.8,
        849.91,
        875.61,
        901.95,
        929.04,
        956.95,
        985.57,
        1015.5
    ],
    "uwnd": [
        32.37,
        34.93,
        37.49,
        40.05,
        42.61,
        45.16,
        47.29,
        47.61,
        47.92,
        48.23,
        48.54,
        48.43,
        48.24,
        48.05,
        47.95,
        48.61,
        49.26,
        49.92,
        49.92,
        49.74,
        49.56,
        49.66,
        49.83,
        50.01,
        48.2,
        46.39,
        44.41,
        42.2,
        40.03,
        39.57,
        39.1,
        38.42,
        37.68,
        36.8,
        35.85,
        34.88,
        33.89,
        32.92,
        31.95,
        30.97,
        29.98,
        28.92,
        27.85,
        26.77,
        25.74,
        24.35,
        22.6,
        20.83,
        17.87,
        14.31,
        10.76,
        8.78,
        6.91,
        5.75,
        5.19,
        4.83,
        4.72,
        4.56,
        4.23,
        3.4,
        1.63,
        -1.29,
        -5.51,
        -8.77,
        -8.14,
        -4.96,
        -0.99
    ],
    "vwnd": [
        -0.89,
        -1.9,
        -2.91,
        -3.92,
        -4.93,
        -5.95,
        -6.54,
        -5.32,
        -4.11,
        -2.9,
        -1.69,
        -0.18,
        1.38,
        2.95,
        4.35,
        4.31,
        4.28,
        4.25,
        3.47,
        2.49,
        1.5,
        0.37,
        -0.8,
        -1.97,
        -2.33,
        -2.67,
        -2.39,
        -1.26,
        -0.15,
        0.03,
        0.21,
        0.86,
        1.66,
        2.68,
        3.81,
        4.74,
        5.57,
        6.08,
        6.5,
        6.62,
        6.6,
        6.22,
        6.02,
        5.95,
        6.14,
        6.49,
        6.99,
        7.52,
        7.57,
        7.34,
        7.05,
        5.53,
        3.91,
        1.8,
        -0.75,
        -3.52,
        -6.42,
        -8.54,
        -9.91,
        -9.97,
        -9.2,
        -8.14,
        -8.43,
        -10.91,
        -12.28,
        -10.24,
        -5.36
    ]
}