{
    "temp": [
        -63.54,
        -63.99,
        -64.45,
        -64.91,
        -65.36,
        -65.82,
        -66.27,
        -66.63,
        -66.14,
        -65.66,
        -65.18,
        -64.69,
        -64.81,
        -65.22,
        -65.62,
        -66.03,
        -64.69,
        -63.21,
        -61.74,
        -60.06,
        -58.28,
        -56.49,
        -54.53,
        -52.5,
        -50.46,
        -48.45,
        -46.43,
        -44.43,
        -42.44,
        -40.43,
        -38.3,
        -36.17,
        -34.05,
        -31.93,
        -29.97,
        -28.04,
        -26.24,
        -24.46,
        -22.72,
        -21.0,
        -19.29,
        -17.59,
        -15.89,
        -14.49,
        -13.15,
        -11.88,
        -10.8,
        -9.72,
        -8.63,
        -7.33,
        -6.09,
        -4.83,
        -3.51,
        -2.14,
        -0.64,
        1.01,
        2.88,
        4.85,
        6.83,
        8.8,
        10.78,
        12.33,
        12.18,
        9.64,
        7.45,
        8.14,
        9.59
    ],
    "dew": [
        -87.79,
        -86.98,
        -86.16,
        -85.34,
        -84.53,
        -83.71,
        -82.89,
        -82.03,
        -80.72,
        -79.41,
        -78.11,
        -76.8,
        -75.4,
        -73.95,
        -72.5,
        -71.05,
        -69.43,
        -67.79,
        -66.15,
        -64.36,
        -62.49,
        -60.61,
        -58.6,
        -56.53,
        -54.46,
        -52.44,
        -50.41,
        -48.5,
        -46.73,
        -44.92,
        -42.86,
        -40.8,
        -38.64,
        -36.46,
        -34.19,
        -31.9,
        -29.75,
        -27.63,
        -25.61,
        -23.61,
        -21.68,
        -19.75,
        -17.83,
        -16.26,
        -14.78,
        -13.39,
        -12.1,
        -10.81,
        -9.48,
        -7.78,
        -6.28,
        -4.89,
        -3.56,
        -2.19,
        -0.71,
        0.63,
        1.74,
        2.59,
        3.47,
        4.48,
        6.07,
        8.64,
        10.77,
        9.45,
        7.39,
        8.04,
        8.89
    ],
    "pres": [
        93.17,
        97.79,
        102.41,
        107.03,
        111.64,
        116.26,
        120.88,
        125.61,
        131.25,
        136.89,
        142.54,
        148.18,
        154.52,
        161.18,
        167.85,
        174.52,
        182.1,
        189.76,
        197.42,
        205.61,
        214.06,
        222.51,
        231.5,
        240.72,
        249.94,
        259.89,
        269.85,
        280.15,
        290.81,
        301.57,
        312.94,
        324.3,
        336.31,
        348.35,
        360.97,
        373.69,
        387.03,
        400.46,
        414.55,
        428.81,
        443.53,
        458.65,
        474.08,
        490.15,
        506.52,
        523.27,
        540.72,
        558.54,
        576.78,
        595.7,
        615.09,
        634.97,
        655.39,
        676.31,
        697.85,
        719.97,
        742.59,
        765.77,
        789.5,
        813.77,
        838.6,
        864.02,
        890.11,
        917.1,
        945.21,
        974.24,
        1003.56
    ],
    "uwnd": [
        18.55,
        21.03,
        23.51,
        25.99,
        28.47,
        30.95,
        33.43,
        35.76,
        36.84,
        37.92,
        39.0,
        40.09,
        44.91,
        51.51,
        58.12,
        64.72,
        65.74,
        66.32,
        66.9,
        65.75,
        63.74,
        61.72,
        60.62,
        59.89,
        59.17,
        57.42,
        55.67,
        53.98,
        52.37,
        50.87,
        50.11,
        49.35,
        48.4,
        47.42,
        46.01,
        44.52,
        43.38,
        42.29,
        41.56,
        40.85,
        40.21,
        39.42,
        38.53,
        36.89,
        35.09,
        33.12,
        30.63,
        28.25,
        26.19,
        25.47,
        24.88,
        24.78,
        25.14,
        25.42,
        25.6,
        25.81,
        26.01,
        25.96,
        25.67,
        25.32,
        25.1,
        25.03,
        24.05,
        19.92,
        12.44,
        6.32,
        2.32
    ],
    "vwnd": [
        1.46,
        2.46,
        3.46,
        4.46,
        5.46,
        6.46,
        7.46,
        8.37,
        8.52,
        8.68,
        8.83,
        8.98,
        9.0,
        8.95,
        8.9,
        8.85,
        10.1,
        11.45,
        12.8,
        12.6,
        11.62,
        10.63,
        9.88,
        9.22,
        8.56,
        9.38,
        10.21,
        11.21,
        12.38,
        13.53,
        14.53,
        15.53,
        15.98,
        16.38,
        16.62,
        16.83,
        17.33,
        17.86,
        18.45,
        19.0,
        19.46,
        19.7,
        19.79,
        19.57,
        19.33,
        19.07,
        18.85,
        18.59,
        18.25,
        17.5,
        16.93,
        16.57,
        16.47,
        16.65,
        17.1,
        17.18,
        17.01,
        16.67,
        16.49,
        16.87,
        18.06,
        19.78,
        21.49,
        21.56,
        17.93,
        11.86,
        4.65
    ]
}