{
    "temp": [
        -50.52,
        -50.44,
        -50.36,
        -50.28,
        -50.2,
        -50.12,
        -50.05,
        -49.97,
        -49.89,
        -49.81,
        -49.73,
        -49.72,
        -49.74,
        -49.76,
        -49.78,
        -49.79,
        -49.82,
        -49.86,
        -49.89,
        -49.92,
        -49.97,
        -50.01,
        -50.06,
        -50.17,
        -50.39,
        -50.61,
        -50.9,
        -51.33,
        -51.77,
        -52.08,
        -52.3,
        -52.53,
        -52.84,
        -53.15,
        -53.79,
        -54.47,
        -53.85,
        -52.96,
        -50.77,
        -48.46,
        -46.02,
        -43.72,
        -41.61,
        -39.7,
        -37.89,
        -36.18,
        -34.42,
        -32.62,
        -30.78,
        -28.86,
        -27.0,
        -25.21,
        -23.48,
        -21.93,
        -20.4,
        -18.97,
        -17.62,
        -16.34,
        -15.11,
        -14.1,
        -13.63,
        -13.79,
        -14.34,
        -15.21,
        -16.53,
        -17.3,
        -16.25
    ],
    "dew": [
        -87.41,
        -87.38,
        -87.36,
        -87.33,
        -87.31,
        -87.28,
        -87.26,
        -87.23,
        -87.21,
        -87.18,
        -87.16,
        -87.29,
        -87.5,
        -87.71,
        -87.93,
        -88.14,
        -87.61,
        -87.01,
        -86.42,
        -85.83,
        -85.44,
        -85.08,
        -84.72,
        -84.25,
        -83.62,
        -82.98,
        -82.27,
        -81.4,
        -80.53,
        -78.67,
        -76.14,
        -73.58,
        -70.82,
        -68.05,
        -65.6,
        -63.18,
        -60.47,
        -57.7,
        -55.23,
        -52.78,
        -50.32,
        -47.94,
        -45.69,
        -43.85,
        -42.19,
        -40.79,
        -39.59,
        -38.29,
        -36.61,
        -34.54,
        -32.35,
        -30.17,
        -28.12,
        -26.12,
        -24.23,
        -22.33,
        -20.49,
        -18.78,
        -17.28,
        -16.18,
        -15.62,
        -15.65,
        -16.17,
        -17.06,
        -18.57,
        -19.61,
        -19.73
    ],
    "pres": [
        80.79,
        85.07,
        89.36,
        93.64,
        97.93,
        102.21,
        106.5,
        110.78,
        115.07,
        119.35,
        123.64,
        128.58,
        133.83,
        139.07,
        144.32,
        149.56,
        155.69,
        161.89,
        168.1,
        174.3,
        181.36,
        188.53,
        195.7,
        203.26,
        211.4,
        219.54,
        228.0,
        237.14,
        246.28,
        256.02,
        266.17,
        276.44,
        287.58,
        298.73,
        310.78,
        322.95,
        335.93,
        349.07,
        362.94,
        376.96,
        391.58,
        406.5,
        421.82,
        437.68,
        453.84,
        470.55,
        487.82,
        505.5,
        523.63,
        542.41,
        561.66,
        581.4,
        601.62,
        622.55,
        644.01,
        666.09,
        688.8,
        712.13,
        736.13,
        760.83,
        786.28,
        812.56,
        839.77,
        867.95,
        897.19,
        927.6,
        958.91
    ],
    "uwnd": [
        21.84,
        21.95,
        22.06,
        22.16,
        22.27,
        22.38,
        22.49,
        22.59,
        22.7,
        22.81,
        22.92,
        23.3,
        23.8,
        24.3,
        24.8,
        25.31,
        26.21,
        27.14,
        28.08,
        29.02,
        29.55,
        30.02,
        30.5,
        30.72,
        30.55,
        30.38,
        30.22,
        30.1,
        29.98,
        29.53,
        28.86,
        28.06,
        26.29,
        24.53,
        22.16,
        19.71,
        17.61,
        15.57,
        15.0,
        14.64,
        14.87,
        15.02,
        15.08,
        14.98,
        14.81,
        14.55,
        14.33,
        14.2,
        14.22,
        14.4,
        14.67,
        15.04,
        15.46,
        15.54,
        15.55,
        15.33,
        15.05,
        14.83,
        14.71,
        14.56,
        14.18,
        13.66,
        13.37,
        12.82,
        10.28,
        5.32,
        1.03
    ],
    "vwnd": [
        5.87,
        5.74,
        5.61,
        5.48,
        5.35,
        5.22,
        5.09,
        4.96,
        4.83,
        4.7,
        4.57,
        4.33,
        4.03,
        3.73,
        3.44,
        3.14,
        3.31,
        3.52,
        3.73,
        3.94,
        4.53,
        5.16,
        5.8,
        6.16,
        6.11,
        6.05,
        5.89,
        5.5,
        5.11,
        4.74,
        4.37,
        3.95,
        3.06,
        2.18,
        1.5,
        0.85,
        0.46,
        0.13,
        -0.16,
        -0.45,
        -0.76,
        -1.01,
        -1.2,
        -1.31,
        -1.39,
        -1.44,
        -1.49,
        -1.58,
        -1.74,
        -1.93,
        -2.12,
        -2.32,
        -2.48,
        -2.43,
        -2.28,
        -1.83,
        -1.2,
        -0.45,
        0.14,
        0.51,
        0.9,
        1.27,
        1.89,
        3.63,
        5.78,
        6.29,
        2.8
    ]
}