{
    "temp": [
        -71.92,
        -70.93,
        -69.94,
        -68.96,
        -67.97,
        -66.98,
        -65.99,
        -65.07,
        -64.17,
        -63.26,
        -62.36,
        -61.77,
        -62.09,
        -62.4,
        -62.72,
        -62.42,
        -61.33,
        -60.25,
        -59.03,
        -57.0,
        -54.96,
        -52.92,
        -50.84,
        -48.75,
        -46.69,
        -44.66,
        -42.64,
        -40.66,
        -38.69,
        -36.79,
        -34.95,
        -33.11,
        -31.27,
        -29.44,
        -27.65,
        -25.89,
        -24.29,
        -22.72,
        -21.2,
        -19.71,
        -18.26,
        -16.81,
        -15.34,
        -13.8,
        -12.26,
        -10.72,
        -9.03,
        -7.43,
        -5.87,
        -4.32,
        -2.85,
        -1.43,
        -0.02,
        1.45,
        3.02,
        5.09,
        7.38,
        9.57,
        11.35,
        12.79,
        13.96,
        15.06,
        16.01,
        17.01,
        17.99,
        19.0,
        20.4
    ],
    "dew": [
        -84.96,
        -84.71,
        -84.46,
        -84.2,
        -83.95,
        -83.7,
        -83.45,
        -82.46,
        -81.19,
        -79.92,
        -78.65,
        -77.29,
        -75.67,
        -74.04,
        -72.41,
        -70.43,
        -68.01,
        -65.58,
        -63.22,
        -61.2,
        -59.19,
        -57.16,
        -55.03,
        -52.9,
        -50.79,
        -48.7,
        -46.62,
        -44.65,
        -42.71,
        -40.74,
        -38.74,
        -36.72,
        -34.6,
        -32.5,
        -30.5,
        -28.53,
        -26.76,
        -25.02,
        -23.37,
        -21.76,
        -20.18,
        -18.61,
        -17.02,
        -15.36,
        -13.78,
        -12.2,
        -10.51,
        -9.04,
        -7.81,
        -6.87,
        -5.95,
        -4.94,
        -3.88,
        -2.79,
        -1.69,
        -0.97,
        -0.38,
        1.08,
        3.12,
        5.34,
        7.16,
        8.79,
        13.07,
        16.54,
        17.66,
        17.35,
        18.37
    ],
    "pres": [
        95.68,
        100.36,
        105.03,
        109.71,
        114.38,
        119.06,
        123.74,
        129.08,
        134.66,
        140.25,
        145.84,
        151.67,
        158.23,
        164.78,
        171.34,
        178.35,
        185.93,
        193.5,
        201.19,
        209.55,
        217.92,
        226.4,
        235.5,
        244.59,
        253.99,
        263.82,
        273.66,
        284.09,
        294.61,
        305.48,
        316.71,
        328.13,
        340.06,
        352.11,
        364.74,
        377.5,
        390.82,
        404.37,
        418.39,
        432.77,
        447.45,
        462.73,
        478.27,
        494.38,
        510.88,
        527.71,
        545.17,
        563.02,
        581.27,
        600.01,
        619.32,
        639.13,
        659.43,
        680.22,
        701.55,
        723.48,
        745.85,
        768.77,
        792.22,
        816.21,
        840.8,
        866.03,
        891.89,
        918.4,
        945.56,
        973.43,
        1001.93
    ],
    "uwnd": [
        33.06,
        33.99,
        34.91,
        35.84,
        36.76,
        37.69,
        38.61,
        40.44,
        42.59,
        44.75,
        46.9,
        49.03,
        51.09,
        53.15,
        55.2,
        55.55,
        53.75,
        51.94,
        49.97,
        47.03,
        44.09,
        41.09,
        37.77,
        34.45,
        31.99,
        30.76,
        29.53,
        29.58,
        29.84,
        29.73,
        29.25,
        28.8,
        28.47,
        28.24,
        28.56,
        28.91,
        29.38,
        29.91,
        30.59,
        31.31,
        32.06,
        32.81,
        33.31,
        32.89,
        32.23,
        31.36,
        30.01,
        28.66,
        27.31,
        25.92,
        24.44,
        22.87,
        21.27,
        19.64,
        17.97,
        16.43,
        15.09,
        13.83,
        12.47,
        10.91,
        9.23,
        7.75,
        6.44,
        4.21,
        0.33,
        -2.32,
        -1.92
    ],
    "vwnd": [
        18.01,
        18.75,
        19.5,
        20.25,
        20.99,
        21.74,
        22.49,
        22.33,
        21.82,
        21.32,
        20.82,
        20.51,
        20.76,
        21.0,
        21.25,
        21.31,
        21.14,
        20.97,
        20.68,
        19.65,
        18.63,
        17.67,
        17.11,
        16.54,
        15.99,
        15.46,
        14.94,
        14.81,
        14.74,
        14.95,
        15.45,
        15.83,
        15.89,
        15.91,
        15.7,
        15.5,
        15.28,
        15.12,
        15.11,
        15.15,
        15.24,
        15.46,
        15.79,
        16.48,
        17.24,
        17.97,
        18.26,
        18.53,
        18.73,
        18.83,
        19.04,
        19.45,
        19.74,
        19.56,
        18.69,
        17.06,
        15.2,
        13.87,
        13.98,
        15.39,
        17.5,
        19.29,
        20.05,
        19.65,
        17.63,
        13.02,
        5.05
    ]
}