{
    "temp": [
        -58.05,
        -57.43,
        -56.81,
        -56.19,
        -55.57,
        -54.95,
        -54.33,
        -53.71,
        -52.92,
        -51.74,
        -50.55,
        -49.37,
        -48.19,
        -47.22,
        -46.41,
        -45.61,
        -44.8,
        -44.31,
        -44.19,
        -44.07,
        -43.96,
        -43.81,
        -43.67,
        -43.52,
        -43.51,
        -43.55,
        -43.59,
        -44.1,
        -44.67,
        -45.04,
        -44.99,
        -44.93,
        -44.28,
        -43.62,
        -42.77,
        -41.89,
        -40.81,
        -39.69,
        -38.5,
        -37.33,
        -36.19,
        -35.02,
        -33.82,
        -32.37,
        -30.81,
        -29.12,
        -27.37,
        -25.64,
        -23.94,
        -22.23,
        -20.43,
        -18.69,
        -17.12,
        -15.78,
        -14.62,
        -13.72,
        -12.95,
        -12.17,
        -11.43,
        -10.51,
        -9.57,
        -8.56,
        -7.54,
        -6.66,
        -5.76,
        -4.28,
        -1.7
    ],
    "dew": [
        -85.69,
        -85.4,
        -85.11,
        -84.82,
        -84.52,
        -84.23,
        -83.94,
        -83.65,
        -83.4,
        -83.27,
        -83.13,
        -82.99,
        -82.85,
        -82.49,
        -81.96,
        -81.42,
        -80.89,
        -80.23,
        -79.43,
        -78.63,
        -77.82,
        -76.93,
        -76.02,
        -75.11,
        -74.71,
        -74.51,
        -74.32,
        -74.27,
        -74.25,
        -73.88,
        -72.81,
        -71.73,
        -70.64,
        -69.54,
        -68.42,
        -67.29,
        -66.85,
        -66.51,
        -66.37,
        -65.66,
        -62.91,
        -59.42,
        -55.29,
        -50.8,
        -46.15,
        -41.31,
        -37.59,
        -33.55,
        -29.47,
        -26.35,
        -23.63,
        -21.29,
        -19.3,
        -17.67,
        -16.35,
        -15.36,
        -14.51,
        -13.64,
        -12.82,
        -11.79,
        -10.67,
        -9.38,
        -8.3,
        -7.86,
        -7.35,
        -6.89,
        -4.07
    ],
    "pres": [
        91.17,
        95.57,
        99.96,
        104.36,
        108.76,
        113.16,
        117.56,
        121.96,
        126.62,
        131.89,
        137.15,
        142.41,
        147.68,
        153.4,
        159.5,
        165.59,
        171.69,
        178.19,
        185.17,
        192.15,
        199.13,
        206.92,
        214.83,
        222.73,
        231.29,
        240.11,
        248.94,
        258.61,
        268.4,
        278.52,
        289.29,
        300.07,
        311.73,
        323.39,
        335.78,
        348.29,
        361.5,
        374.82,
        388.93,
        403.23,
        418.13,
        433.45,
        449.11,
        465.49,
        482.24,
        499.43,
        517.21,
        535.45,
        554.17,
        573.34,
        593.21,
        613.53,
        634.37,
        655.8,
        677.81,
        700.48,
        723.89,
        747.99,
        772.83,
        798.39,
        824.68,
        851.79,
        879.67,
        908.36,
        937.87,
        968.18,
        999.93
    ],
    "uwnd": [
        26.01,
        27.26,
        28.5,
        29.74,
        30.99,
        32.23,
        33.47,
        34.72,
        35.82,
        36.62,
        37.42,
        38.22,
        39.02,
        39.46,
        39.61,
        39.75,
        39.9,
        40.05,
        40.2,
        40.35,
        40.5,
        41.68,
        43.0,
        44.32,
        44.69,
        44.68,
        44.68,
        43.67,
        42.54,
        41.57,
        40.94,
        40.3,
        39.19,
        38.07,
        36.12,
        34.05,
        31.57,
        29.02,
        26.35,
        23.7,
        21.14,
        18.81,
        16.69,
        15.35,
        14.35,
        13.75,
        13.44,
        13.57,
        14.05,
        14.63,
        15.39,
        16.13,
        16.76,
        17.3,
        17.82,
        18.2,
        17.71,
        16.56,
        14.43,
        12.36,
        10.32,
        8.12,
        5.49,
        2.62,
        0.92,
        0.06,
        -0.06
    ],
    "vwnd": [
        0.12,
        0.29,
        0.47,
        0.65,
        0.83,
        1.0,
        1.18,
        1.36,
        1.62,
        2.05,
        2.49,
        2.92,
        3.36,
        3.66,
        3.84,
        4.03,
        4.21,
        3.8,
        2.67,
        1.54,
        0.41,
        -0.09,
        -0.49,
        -0.9,
        -0.63,
        -0.09,
        0.46,
        0.22,
        -0.12,
        -0.57,
        -1.23,
        -1.88,
        -1.85,
        -1.82,
        -1.4,
        -0.93,
        -0.36,
        0.22,
        0.99,
        1.74,
        2.45,
        3.13,
        3.79,
        4.32,
        4.82,
        5.3,
        5.71,
        5.76,
        5.52,
        5.14,
        4.15,
        3.11,
        2.08,
        1.19,
        0.71,
        0.84,
        1.57,
        2.6,
        3.21,
        3.48,
        3.85,
        4.53,
        4.74,
        4.43,
        4.31,
        3.34,
        1.98
    ]
}