{
    "temp": [
        -68.22,
        -67.83,
        -67.44,
        -67.05,
        -66.66,
        -66.27,
        -65.88,
        -65.49,
        -65.09,
        -64.55,
        -63.89,
        -63.24,
        -62.58,
        -62.21,
        -64.14,
        -66.08,
        -68.01,
        -68.86,
        -67.85,
        -66.84,
        -65.7,
        -63.86,
        -62.02,
        -60.05,
        -57.75,
        -55.45,
        -53.11,
        -50.74,
        -48.39,
        -46.14,
        -43.89,
        -41.74,
        -39.61,
        -37.55,
        -35.51,
        -33.53,
        -31.57,
        -29.69,
        -27.85,
        -26.15,
        -24.48,
        -22.85,
        -21.23,
        -19.63,
        -18.02,
        -16.42,
        -14.89,
        -13.35,
        -11.85,
        -10.4,
        -8.99,
        -7.67,
        -6.43,
        -5.3,
        -4.35,
        -3.53,
        -3.04,
        -2.64,
        -2.36,
        -2.15,
        -2.17,
        -2.33,
        -2.18,
        -1.7,
        -3.06,
        -4.55,
        -3.4
    ],
    "dew": [
        -86.63,
        -86.47,
        -86.3,
        -86.14,
        -85.98,
        -85.82,
        -85.66,
        -85.5,
        -85.34,
        -84.46,
        -83.06,
        -81.66,
        -80.26,
        -78.86,
        -77.47,
        -76.08,
        -74.69,
        -73.4,
        -72.27,
        -71.14,
        -69.89,
        -68.03,
        -66.17,
        -64.18,
        -61.86,
        -59.55,
        -57.13,
        -54.65,
        -52.19,
        -49.89,
        -47.59,
        -45.37,
        -43.17,
        -41.0,
        -38.85,
        -36.72,
        -34.61,
        -32.58,
        -30.59,
        -28.74,
        -26.92,
        -25.17,
        -23.43,
        -21.72,
        -19.92,
        -18.14,
        -16.49,
        -14.79,
        -13.14,
        -11.56,
        -10.05,
        -8.66,
        -7.36,
        -6.16,
        -5.12,
        -4.18,
        -3.57,
        -3.13,
        -2.87,
        -2.73,
        -2.87,
        -2.92,
        -2.34,
        -1.74,
        -3.11,
        -4.96,
        -4.75
    ],
    "pres": [
        86.1,
        90.72,
        95.34,
        99.96,
        104.58,
        109.21,
        113.83,
        118.45,
        123.07,
        128.26,
        133.85,
        139.43,
        145.02,
        150.73,
        157.41,
        164.09,
        170.77,
        177.87,
        185.69,
        193.5,
        201.46,
        210.11,
        218.75,
        227.61,
        237.01,
        246.42,
        256.27,
        266.41,
        276.64,
        287.44,
        298.24,
        309.63,
        321.14,
        333.1,
        345.3,
        357.92,
        370.8,
        384.15,
        397.72,
        411.88,
        426.21,
        441.12,
        456.33,
        471.95,
        488.17,
        504.7,
        521.63,
        539.18,
        557.11,
        575.43,
        594.45,
        613.93,
        633.9,
        654.41,
        675.48,
        697.23,
        719.64,
        742.7,
        766.46,
        790.96,
        816.22,
        842.3,
        869.23,
        896.95,
        925.55,
        955.44,
        986.56
    ],
    "uwnd": [
        41.19,
        41.1,
        41.02,
        40.93,
        40.85,
        40.76,
        40.68,
        40.59,
        40.51,
        40.89,
        41.61,
        42.34,
        43.06,
        44.3,
        49.76,
        55.21,
        60.67,
        63.63,
        62.29,
        60.96,
        59.12,
        54.75,
        50.38,
        46.59,
        44.28,
        41.98,
        40.26,
        38.89,
        37.59,
        36.58,
        35.58,
        34.85,
        34.18,
        33.6,
        33.06,
        32.4,
        31.65,
        30.61,
        29.43,
        27.91,
        26.3,
        24.58,
        22.9,
        21.29,
        20.14,
        19.15,
        18.32,
        17.63,
        17.0,
        16.42,
        15.85,
        15.34,
        14.88,
        14.45,
        13.95,
        13.47,
        13.51,
        13.71,
        13.9,
        13.57,
        11.76,
        7.74,
        1.23,
        -6.1,
        -11.72,
        -12.58,
        -5.76
    ],
    "vwnd": [
        -3.07,
        -1.78,
        -0.5,
        0.79,
        2.07,
        3.35,
        4.64,
        5.92,
        7.2,
        8.04,
        8.56,
        9.07,
        9.59,
        10.37,
        13.28,
        16.19,
        19.1,
        21.25,
        22.12,
        22.98,
        23.72,
        23.9,
        24.07,
        24.31,
        24.7,
        25.08,
        25.3,
        25.41,
        25.44,
        25.0,
        24.57,
        23.7,
        22.74,
        21.62,
        20.41,
        19.32,
        18.3,
        17.46,
        16.7,
        15.89,
        15.05,
        14.0,
        12.86,
        11.58,
        10.18,
        8.77,
        7.42,
        6.39,
        5.67,
        5.35,
        6.02,
        7.05,
        8.44,
        9.98,
        11.05,
        11.71,
        11.4,
        11.22,
        11.62,
        13.48,
        16.16,
        18.98,
        21.63,
        23.48,
        21.08,
        12.69,
        4.99
    ]
}