{
    "temp": [
        -67.83,
        -66.97,
        -66.1,
        -65.23,
        -64.37,
        -63.5,
        -62.64,
        -61.77,
        -60.95,
        -60.16,
        -59.36,
        -58.57,
        -57.91,
        -58.19,
        -58.47,
        -58.75,
        -59.2,
        -60.18,
        -61.16,
        -62.14,
        -60.97,
        -59.63,
        -58.28,
        -56.02,
        -53.76,
        -51.54,
        -49.41,
        -47.28,
        -45.45,
        -43.68,
        -41.89,
        -40.08,
        -38.17,
        -36.06,
        -33.91,
        -31.66,
        -29.41,
        -27.18,
        -25.16,
        -23.37,
        -21.76,
        -20.21,
        -18.66,
        -17.02,
        -15.27,
        -13.45,
        -11.71,
        -10.11,
        -8.6,
        -7.31,
        -6.16,
        -4.95,
        -3.29,
        -1.71,
        -0.18,
        1.18,
        2.26,
        3.08,
        3.17,
        2.19,
        0.3,
        -1.96,
        -3.74,
        -3.42,
        -2.4,
        -0.87,
        1.25
    ],
    "dew": [
        -85.07,
        -84.71,
        -84.34,
        -83.98,
        -83.61,
        -83.24,
        -82.88,
        -82.51,
        -81.88,
        -81.13,
        -80.38,
        -79.63,
        -78.78,
        -77.31,
        -75.85,
        -74.38,
        -72.98,
        -71.8,
        -70.61,
        -69.42,
        -67.53,
        -65.59,
        -63.64,
        -61.46,
        -59.27,
        -57.26,
        -55.63,
        -54.01,
        -53.94,
        -54.2,
        -54.23,
        -54.03,
        -53.71,
        -53.19,
        -52.69,
        -52.27,
        -51.95,
        -51.86,
        -51.27,
        -50.14,
        -47.97,
        -45.35,
        -41.76,
        -38.87,
        -36.96,
        -35.53,
        -34.49,
        -33.95,
        -33.46,
        -33.24,
        -33.01,
        -32.21,
        -29.21,
        -26.63,
        -24.38,
        -21.46,
        -17.28,
        -13.15,
        -9.4,
        -7.18,
        -5.56,
        -3.95,
        -3.89,
        -3.47,
        -2.44,
        -0.94,
        0.11
    ],
    "pres": [
        91.54,
        96.11,
        100.68,
        105.26,
        109.83,
        114.41,
        118.98,
        123.55,
        128.75,
        134.24,
        139.73,
        145.22,
        150.83,
        157.27,
        163.7,
        170.14,
        176.85,
        184.38,
        191.91,
        199.44,
        207.92,
        216.47,
        225.03,
        234.33,
        243.62,
        253.15,
        263.18,
        273.21,
        283.82,
        294.56,
        305.67,
        317.16,
        328.87,
        341.06,
        353.43,
        366.3,
        379.37,
        392.89,
        406.71,
        420.88,
        435.52,
        450.37,
        465.92,
        481.76,
        498.02,
        514.78,
        531.9,
        549.48,
        567.6,
        586.18,
        605.25,
        624.78,
        645.02,
        665.72,
        686.93,
        708.69,
        731.03,
        753.97,
        777.6,
        801.98,
        827.31,
        853.65,
        881.04,
        909.38,
        938.53,
        968.46,
        999.56
    ],
    "uwnd": [
        38.03,
        39.11,
        40.19,
        41.28,
        42.36,
        43.45,
        44.53,
        45.62,
        47.21,
        49.03,
        50.85,
        52.68,
        54.26,
        54.2,
        54.15,
        54.09,
        54.72,
        57.43,
        60.14,
        62.85,
        61.96,
        60.79,
        59.62,
        58.48,
        57.35,
        56.49,
        56.26,
        56.03,
        54.55,
        52.79,
        50.78,
        48.49,
        46.63,
        45.73,
        44.99,
        44.74,
        44.36,
        43.69,
        42.08,
        39.43,
        35.94,
        32.1,
        28.63,
        25.86,
        24.06,
        22.94,
        21.95,
        21.02,
        20.04,
        18.84,
        17.49,
        16.14,
        14.86,
        13.99,
        13.63,
        13.63,
        13.59,
        12.86,
        9.69,
        5.32,
        0.6,
        -2.73,
        -5.05,
        -6.76,
        -6.7,
        -4.91,
        -2.37
    ],
    "vwnd": [
        -1.28,
        -1.12,
        -0.96,
        -0.81,
        -0.65,
        -0.49,
        -0.34,
        -0.18,
        -0.42,
        -0.83,
        -1.25,
        -1.66,
        -1.95,
        -1.39,
        -0.83,
        -0.26,
        0.91,
        3.97,
        7.03,
        10.09,
        13.25,
        16.43,
        19.58,
        19.27,
        18.96,
        17.97,
        15.46,
        12.96,
        9.54,
        5.91,
        3.23,
        1.52,
        0.23,
        -0.13,
        -0.44,
        -0.6,
        -1.0,
        -1.89,
        -2.95,
        -4.22,
        -5.42,
        -6.56,
        -6.59,
        -6.7,
        -6.92,
        -7.25,
        -7.65,
        -8.15,
        -8.44,
        -8.13,
        -7.37,
        -6.5,
        -4.96,
        -3.56,
        -2.36,
        -1.61,
        -1.43,
        -1.49,
        -1.79,
        -2.91,
        -4.42,
        -5.31,
        -5.32,
        -5.08,
        -6.62,
        -6.75,
        -4.26
    ]
}